yapij/WorkspaceManager.py
yapij/ZMQIOWrapper.py
yapij/__init__.py
yapij/client.py
yapij/config.py
yapij/context.py
yapij/exceptions.py
yapij/magic.py
yapij/manager.py
yapij/parse.py
yapij/printing.py
yapij/run.py
yapij/session.py
yapij/status_msg.py
yapij/threading2.py
yapij/utils.py
yapij/workers.py
yapij/packers/__init__.py
yapij/packers/fmt_pandas.py
yapij/packers/fmt_special.py
yapij/packers/packers.py
yapij_py-999.dist-info/METADATA
yapij_py-999.dist-info/WHEEL
yapij_py-999.dist-info/top_level.txt
yapij_py-999.dist-info/RECORD
