Metadata-Version: 2.1
Name: yapij-py
Version: 999
Summary: Python-side of YAPIJ js-to-python interpreter.
Home-page: https://github.com/michaelwooley/yapij
Author: Michael Wooley
Author-email: michael.wooley@us.gt.com
License: UNKNOWN
Platform: UNKNOWN
Classifier: Development Status :: 3 - Alpha
Classifier: Programming Language :: Python :: 3.7
Classifier: Operating System :: OS Independent
Requires-Python: >=3.5
Requires-Dist: dill
Requires-Dist: traitlets
Requires-Dist: typing
Requires-Dist: msgpack-python
Requires-Dist: pyzmq
